random_byte_array.py
random_byte_array-0.1.0a0.dist-info/licenses/LICENSE
random_byte_array-0.1.0a0.dist-info/METADATA
random_byte_array-0.1.0a0.dist-info/WHEEL
random_byte_array-0.1.0a0.dist-info/top_level.txt
random_byte_array-0.1.0a0.dist-info/RECORD
