Metadata-Version: 2.4
Name: random-byte-array
Version: 0.1.0a0
Summary: A lightweight Python utility for generating random byte arrays.
Author-email: Jifeng Wu <jifengwu2k@gmail.com>
License-Expression: AGPL-3.0
Project-URL: Homepage, https://github.com/jifengwu2k/random-byte-array
Project-URL: Bug Tracker, https://github.com/jifengwu2k/random-byte-array/issues
Classifier: Programming Language :: Python :: 2
Classifier: Programming Language :: Python :: 3
Classifier: Operating System :: OS Independent
Requires-Python: >=2
License-File: LICENSE
Dynamic: license-file
